elasticstats/__about__.py
elasticstats/__init__.py
elasticstats/carbon.py
elasticstats/es.py
elasticstats/main.py
elasticstats-0.3.1.dist-info/DESCRIPTION.rst
elasticstats-0.3.1.dist-info/METADATA
elasticstats-0.3.1.dist-info/RECORD
elasticstats-0.3.1.dist-info/WHEEL
elasticstats-0.3.1.dist-info/entry_points.txt
elasticstats-0.3.1.dist-info/metadata.json
elasticstats-0.3.1.dist-info/top_level.txt
