Metadata-Version: 2.0
Name: elasticstats
Version: 0.3.1
Summary: elasticstats populates a Graphite server with stats from Elasticsearch
Home-page: https://github.com/lyst/elasticstats
Author: Lyst Ltd
Author-email: info@lyst.com
License: LGPLv3
Platform: UNKNOWN
Requires-Dist: future
